pyxr/__init__.py
pyxr/pyxr.py
pyxr-1.0.6.dist-info/DESCRIPTION.rst
pyxr-1.0.6.dist-info/METADATA
pyxr-1.0.6.dist-info/RECORD
pyxr-1.0.6.dist-info/WHEEL
pyxr-1.0.6.dist-info/metadata.json
pyxr-1.0.6.dist-info/top_level.txt
