Metadata-Version: 2.0
Name: pyxr
Version: 1.0.6
Summary: An object-relational mapping-ish wrapper around Xlib and X's resource manager/xrdb
Home-page: https://github.com/WhatNodyn/Pyxr
Author: Neil Cecchini
Author-email: stranger.neil@gmail.com
License: MIT
Platform: UNKNOWN
Classifier: Development Status :: 3 - Alpha
Classifier: Intended Audience :: Developers
Classifier: Topic :: Software Development :: Libraries
Classifier: Programming Language :: Python :: 3 :: Only
Requires-Dist: python-xlib
